labcli44044-0.1.3.dist-info/licenses/LICENSE
labmanager/__init__.py
labmanager/cli.py
labmanager/program/Average_Temperature_by_City.py
labmanager/program/Classification_using_Naïve Bayes.py
labmanager/program/Dictionary_Operations.py
labmanager/program/File_Handling_in_Python.py
labmanager/program/Geographic_Data_Visualization.py
labmanager/program/Histograms_and_Boxplots.py
labmanager/program/Inverted_ Index.py
labmanager/program/K-Means_Clustering.py
labmanager/program/Line_and_Bar_Charts.py
labmanager/program/Linear_Regression.py
labmanager/program/List_Manipulations.py
labmanager/program/Logistic_Regression.py
labmanager/program/Matrix–Vector_Multiplication.py
labmanager/program/Model_Evaluation_using_Confusion_Matrix.py
labmanager/program/Scatter_Plot_and_Correlation_Analysis.py
labmanager/program/Sorting_by_Key.py
labmanager/program/String_Operations.py
labmanager/program/Time_Series_Visualization.py
labmanager/program/Tuple_and_Set_Operations.py
labmanager/program/Word_Count.py
labmanager/program/__init__.py
labcli44044-0.1.3.dist-info/METADATA
labcli44044-0.1.3.dist-info/WHEEL
labcli44044-0.1.3.dist-info/entry_points.txt
labcli44044-0.1.3.dist-info/top_level.txt
labcli44044-0.1.3.dist-info/RECORD
