Metadata-Version: 2.4
Name: labcli44044
Version: 0.1.3
Summary: CLI to list and run lab programs stored in a programs/ directory
Author: labuser
License: MIT License
Project-URL: Homepage, https://github.com/Shakthi44044/labcli
Project-URL: Bug Tracker, https://github.com/Shakthi44044/labcli/issues
Requires-Python: >=3.8
License-File: LICENSE
Dynamic: license-file
